<?xml version="1.0" encoding="UTF-8"?><record_update table="sys_scope_privilege">
    <sys_scope_privilege action="DELETE">
        <operation>read</operation>
        <source_scope display_value="Ingram Micro IT Asset Disposition">df95bbf0dbc17f008a521fe968961950</source_scope>
        <status>allowed</status>
        <sys_class_name>sys_scope_privilege</sys_class_name>
        <sys_created_by>Munimohan.Bathala@ness.com</sys_created_by>
        <sys_created_on>2020-06-02 13:43:24</sys_created_on>
        <sys_customer_update>false</sys_customer_update>
        <sys_id>a1895213db0d50108a521fe96896196e</sys_id>
        <sys_mod_count>0</sys_mod_count>
        <sys_name>sys_dictionary</sys_name>
        <sys_package display_value="Ingram Micro IT Asset Disposition" source="x_inmis_im_itad">df95bbf0dbc17f008a521fe968961950</sys_package>
        <sys_policy/>
        <sys_replace_on_upgrade>false</sys_replace_on_upgrade>
        <sys_scope display_value="Ingram Micro IT Asset Disposition">df95bbf0dbc17f008a521fe968961950</sys_scope>
        <sys_update_name>sys_scope_privilege_a1895213db0d50108a521fe96896196e</sys_update_name>
        <sys_updated_by>Munimohan.Bathala@ness.com</sys_updated_by>
        <sys_updated_on>2020-06-02 13:43:24</sys_updated_on>
        <target_name>sys_dictionary</target_name>
        <target_scope display_value="Global">global</target_scope>
        <target_type>sys_db_object</target_type>
    </sys_scope_privilege>
    <sys_update_version action="INSERT_OR_UPDATE">
        <action>DELETE</action>
        <application display_value="Ingram Micro IT Asset Disposition">df95bbf0dbc17f008a521fe968961950</application>
        <file_path/>
        <instance_id>c821e244dbe52b846578f22ebf9619bf</instance_id>
        <instance_name>ven02711</instance_name>
        <name>sys_scope_privilege_a1895213db0d50108a521fe96896196e</name>
        <payload><![CDATA[<?xml version="1.0" encoding="UTF-8"?><record_update table="sys_scope_privilege"><sys_scope_privilege action="INSERT_OR_UPDATE"><operation>read</operation><source_scope display_value="Ingram Micro IT Asset Disposition">df95bbf0dbc17f008a521fe968961950</source_scope><status>allowed</status><sys_class_name>sys_scope_privilege</sys_class_name><sys_created_by>Munimohan.Bathala@ness.com</sys_created_by><sys_created_on>2020-06-02 13:43:24</sys_created_on><sys_customer_update>false</sys_customer_update><sys_id>a1895213db0d50108a521fe96896196e</sys_id><sys_mod_count>0</sys_mod_count><sys_name>sys_dictionary</sys_name><sys_package display_value="Ingram Micro IT Asset Disposition" source="x_inmis_im_itad">df95bbf0dbc17f008a521fe968961950</sys_package><sys_policy/><sys_replace_on_upgrade>false</sys_replace_on_upgrade><sys_scope display_value="Ingram Micro IT Asset Disposition">df95bbf0dbc17f008a521fe968961950</sys_scope><sys_update_name>sys_scope_privilege_a1895213db0d50108a521fe96896196e</sys_update_name><sys_updated_by>Munimohan.Bathala@ness.com</sys_updated_by><sys_updated_on>2020-06-02 13:43:24</sys_updated_on><target_name>sys_dictionary</target_name><target_scope display_value="Global">global</target_scope><target_type>sys_db_object</target_type></sys_scope_privilege></record_update>]]></payload>
        <payload_hash>-2139596967</payload_hash>
        <record_name>sys_dictionary</record_name>
        <reverted_from/>
        <source>937b508fdb0d10108a521fe96896196a</source>
        <source_table>sys_update_set</source_table>
        <state>previous</state>
        <sys_created_by>Munimohan.Bathala@ness.com</sys_created_by>
        <sys_created_on>2020-06-02 13:43:24</sys_created_on>
        <sys_id>ed895213db0d50108a521fe968961970</sys_id>
        <sys_mod_count>0</sys_mod_count>
        <sys_recorded_at>1727545be620000001</sys_recorded_at>
        <sys_updated_by>Munimohan.Bathala@ness.com</sys_updated_by>
        <sys_updated_on>2020-06-02 13:43:24</sys_updated_on>
        <type>Cross scope privilege</type>
        <update_guid>25895213820d5010207280ef8cce1670</update_guid>
        <update_guid_history>25895213820d5010207280ef8cce1670:-2139596967</update_guid_history>
    </sys_update_version>
    <sys_metadata_delete action="INSERT_OR_UPDATE">
        <sys_audit_delete/>
        <sys_class_name>sys_metadata_delete</sys_class_name>
        <sys_created_by>Munimohan.Bathala@ness.com</sys_created_by>
        <sys_created_on>2020-06-02 13:54:16</sys_created_on>
        <sys_db_object display_value="" name="sys_scope_privilege">sys_scope_privilege</sys_db_object>
        <sys_id>6bd6d9804982437897e700549e56cc40</sys_id>
        <sys_metadata>a1895213db0d50108a521fe96896196e</sys_metadata>
        <sys_mod_count>0</sys_mod_count>
        <sys_name>sys_dictionary</sys_name>
        <sys_package display_value="Ingram Micro IT Asset Disposition" source="x_inmis_im_itad">df95bbf0dbc17f008a521fe968961950</sys_package>
        <sys_parent/>
        <sys_policy/>
        <sys_scope display_value="Ingram Micro IT Asset Disposition">df95bbf0dbc17f008a521fe968961950</sys_scope>
        <sys_scope_delete display_value="">754b5651fdcb480ea4d7b0c2cca0f181</sys_scope_delete>
        <sys_update_name>sys_scope_privilege_a1895213db0d50108a521fe96896196e</sys_update_name>
        <sys_update_version display_value="sys_scope_privilege_a1895213db0d50108a521fe96896196e">ed895213db0d50108a521fe968961970</sys_update_version>
        <sys_updated_by>Munimohan.Bathala@ness.com</sys_updated_by>
        <sys_updated_on>2020-06-02 13:54:16</sys_updated_on>
    </sys_metadata_delete>
</record_update>
